MANIFEST.in
README.md
setup.py
sltools/__init__.py
sltools/config_file_manager.py
sltools/log_config_loader.py
sltools/slt.py
sltools.egg-info/PKG-INFO
sltools.egg-info/SOURCES.txt
sltools.egg-info/dependency_links.txt
sltools.egg-info/entry_points.txt
sltools.egg-info/requires.txt
sltools.egg-info/top_level.txt
sltools/baseline/__init__.py
sltools/baseline/command_baseline.py
sltools/baseline/command_processor.py
sltools/baseline/common.py
sltools/baseline/config.py
sltools/baseline/parser_definitions.py
sltools/locale/en/LC_MESSAGES/sltools.mo
sltools/locale/uk/LC_MESSAGES/sltools.mo
sltools/root_commands/AnalyzePatterns.py
sltools/root_commands/CapitalizeText.py
sltools/root_commands/CheckPrimaryLanguage.py
sltools/root_commands/Config.py
sltools/root_commands/FindStringDuplicates.py
sltools/root_commands/FixEncoding.py
sltools/root_commands/FormatXml.py
sltools/root_commands/MO2CommandProcessor.py
sltools/root_commands/Misc.py
sltools/root_commands/SortFilesWithDuplicates.py
sltools/root_commands/Translate.py
sltools/root_commands/ValidateEncoding.py
sltools/root_commands/ValidateXml.py
sltools/root_commands/__init__.py
sltools/root_commands/mo2_commands/VfsCopy.py
sltools/root_commands/mo2_commands/VfsMap.py
sltools/root_commands/mo2_commands/__init__.py
sltools/utils/__init__.py
sltools/utils/colorize.py
sltools/utils/encoding_utils.py
sltools/utils/error_utils.py
sltools/utils/file_utils.py
sltools/utils/git_utils.py
sltools/utils/lang_utils.py
sltools/utils/misc.py
sltools/utils/plain_text_utils.py
sltools/utils/watch_files_for_change.py
sltools/utils/xml_utils.py
sltools/web_server/__init__.py
sltools/web_server/flask_server.py
sltools/web_server/static/styles.css
sltools/web_server/static/assets/download.svg
sltools/web_server/static/assets/radiation.svg
sltools/web_server/static/assets/shutdown.svg
sltools/web_server/static/js/backendCommunication.js
sltools/web_server/static/js/d3.v5.min.js
sltools/web_server/static/js/infoProvider.js
sltools/web_server/static/js/misc.js
sltools/web_server/static/js/renderer.js
sltools/web_server/static/js/script.js
sltools/web_server/static/js/utils.js
sltools/web_server/templates/index.html