Metadata-Version: 2.1
Name: sltools
Version: 0.2.2
Summary: S.T.A.L.K.E.R Localization Toolbox
Home-page: https://github.com/HalavicH/stalker-localization-toolbox
Author: HalavicH
Author-email: HalavicH@gmail.com
License: MIT
Project-URL: Bug Reports, https://github.com/HalavicH/stalker-localization-toolbox/issues/
Project-URL: Source, https://github.com/HalavicH/stalker-localization-toolbox/
Project-URL: Documentation, https://github.com/HalavicH/stalker-localization-toolbox/wiki
Keywords: XML S.T.A.L.K.E.R stalker mods modding game tools translate analysis
Classifier: Development Status :: 3 - Alpha
Classifier: Intended Audience :: Developers
Classifier: License :: OSI Approved :: MIT License
Classifier: Programming Language :: Python :: 3
Classifier: Programming Language :: Python :: 3.8
Classifier: Programming Language :: Python :: 3.9
Classifier: Programming Language :: Python :: 3.10
Classifier: Programming Language :: Python :: 3.11
Classifier: Programming Language :: Python :: 3.12
Requires-Python: >=3.8
Requires-Dist: colorama
Requires-Dist: chardet
Requires-Dist: argparse
Requires-Dist: colorlog
Requires-Dist: requests
Requires-Dist: lxml
Requires-Dist: langdetect
Requires-Dist: prettytable
Requires-Dist: rich
Requires-Dist: rich_argparse
Requires-Dist: GitPython
Requires-Dist: setuptools
Requires-Dist: Flask
Requires-Dist: flask_CORS
Requires-Dist: watchdog
Requires-Dist: googletrans~=4.0.0rc1
